README.rst
setup.py
htmlmarkup/__init__.py
htmlmarkup/constants.py
htmlmarkup/errors.py
htmlmarkup/validators.py
htmlmarkup.egg-info/PKG-INFO
htmlmarkup.egg-info/SOURCES.txt
htmlmarkup.egg-info/dependency_links.txt
htmlmarkup.egg-info/top_level.txt
htmlmarkup/mixins/__init__.py
htmlmarkup/mixins/generators.py
htmlmarkup/tags/__init__.py
htmlmarkup/tags/base.py
test/__init__.py
test/test_tag.py
test/test_validators.py