Metadata-Version: 1.0
Name: htmlmarkup
Version: 0.1
Summary: UNKNOWN
Home-page: UNKNOWN
Author: UNKNOWN
Author-email: UNKNOWN
License: UNKNOWN
Platform: UNKNOWN
